setup.py
fpkbasiccalculator/__init__.py
fpkbasiccalculator.egg-info/PKG-INFO
fpkbasiccalculator.egg-info/SOURCES.txt
fpkbasiccalculator.egg-info/dependency_links.txt
fpkbasiccalculator.egg-info/top_level.txt