Metadata-Version: 1.1
Name: fpkbasiccalculator
Version: 0.0.1
Summary: A very basic calculator
Home-page: UNKNOWN
Author: Md Faisal Alam
Author-email: faisalgbox@gmail.com
License: MIT
Keywords: calculator
Platform: UNKNOWN
Classifier: Development Status :: 5 - Production/Stable
Classifier: Intended Audience :: Education
